{
  "strategy": "volume_breakout",
  "trained_at": "2026-05-16T20:15:50+00:00",
  "samples": 994,
  "wins": 424,
  "win_rate": 0.42655935613682094,
  "status": "trained",
  "oob_score": 0.5513078470824949,
  "feature_importances": [
    {
      "name": "vol_ratio",
      "importance": 0.14712922721191216
    },
    {
      "name": "bias_pct",
      "importance": 0.138340566907567
    },
    {
      "name": "kd_k",
      "importance": 0.13642707165471088
    },
    {
      "name": "atr_normalized",
      "importance": 0.13589155979310868
    },
    {
      "name": "kd_d",
      "importance": 0.12453117045539903
    },
    {
      "name": "macd_osc",
      "importance": 0.11687590711730893
    },
    {
      "name": "macd_dif",
      "importance": 0.11380714735491526
    },
    {
      "name": "bb_position",
      "importance": 0.04057347135913284
    },
    {
      "name": "inst_5d",
      "importance": 0.014536870768673445
    },
    {
      "name": "holders_pct_change_4w",
      "importance": 0.010250212135412409
    },
    {
      "name": "inst_10d",
      "importance": 0.00966797941185815
    },
    {
      "name": "ma_alignment",
      "importance": 0.006499634855957772
    },
    {
      "name": "holders_delta_w_zscore",
      "importance": 0.004275122022187719
    },
    {
      "name": "inst_5d_zscore",
      "importance": 0.001194058951855791
    },
    {
      "name": "regime_dummy",
      "importance": 0.0
    },
    {
      "name": "is_theme_member",
      "importance": 0.0
    }
  ],
  "feature_names": [
    "kd_k",
    "kd_d",
    "macd_dif",
    "macd_osc",
    "ma_alignment",
    "bb_position",
    "vol_ratio",
    "bias_pct",
    "atr_normalized",
    "inst_5d",
    "inst_10d",
    "holders_delta_w_zscore",
    "inst_5d_zscore",
    "regime_dummy",
    "holders_pct_change_4w",
    "is_theme_member"
  ],
  "min_train_samples": 100,
  "lookback_days": 200,
  "target_pct": 0.05,
  "stop_pct": 0.03,
  "hold_days": 5,
  "model_type": "RandomForestClassifier",
  "n_estimators": 200,
  "max_depth": 10,
  "min_samples_leaf": 5,
  "calibration": {
    "method": "platt",
    "n_holdout": 199,
    "raw_brier": 0.16890374994912097,
    "calibrated_brier": 0.14877641516776044,
    "pkl_path": "/home/runner/work/stock-screener/stock-screener/models/calibrators/volume_breakout.pkl"
  }
}